fortnitepy/__init__.py
fortnitepy/auth.py
fortnitepy/client.py
fortnitepy/enums.py
fortnitepy/errors.py
fortnitepy/friend.py
fortnitepy/http.py
fortnitepy/kairos.py
fortnitepy/message.py
fortnitepy/news.py
fortnitepy/party.py
fortnitepy/playlist.py
fortnitepy/presence.py
fortnitepy/stats.py
fortnitepy/store.py
fortnitepy/typedefs.py
fortnitepy/user.py
fortnitepy/utils.py
fortnitepy/websocket.py
fortnitepy/xmpp.py
fortnitepy/ext/commands/__init__.py
fortnitepy/ext/commands/_types.py
fortnitepy/ext/commands/bot.py
fortnitepy/ext/commands/cog.py
fortnitepy/ext/commands/context.py
fortnitepy/ext/commands/converter.py
fortnitepy/ext/commands/cooldown.py
fortnitepy/ext/commands/core.py
fortnitepy/ext/commands/errors.py
fortnitepy/ext/commands/help.py
fortnitepy/ext/commands/typedefs.py
fortnitepy/ext/commands/view.py
fortnitepy_edit-1.1.6.dist-info/METADATA
fortnitepy_edit-1.1.6.dist-info/WHEEL
fortnitepy_edit-1.1.6.dist-info/top_level.txt
fortnitepy_edit-1.1.6.dist-info/RECORD
