Metadata-Version: 2.1
Name: fortnitepy-edit
Version: 1.1.6
Summary: Library for interacting with fortnite services
Author: klld
License: MIT
Project-URL: Documentation, https://fortnitepy.readthedocs.io/en/latest/
Project-URL: Issue tracker, https://github.com/klldtest/fortnitepy-edit/Issue
Classifier: License :: OSI Approved :: MIT License
Classifier: Intended Audience :: Developers
Classifier: Natural Language :: English
Classifier: Operating System :: OS Independent
Classifier: Programming Language :: Python :: 3.5
Classifier: Programming Language :: Python :: 3.6
Classifier: Programming Language :: Python :: 3.7
Classifier: Programming Language :: Python :: 3.8
Classifier: Programming Language :: Python :: 3.9
Classifier: Programming Language :: Python :: 3.10
Classifier: Topic :: Internet
Classifier: Topic :: Software Development :: Libraries
Classifier: Topic :: Software Development :: Libraries :: Python Modules
Classifier: Topic :: Utilities
Requires-Python: >=3.5.3
Requires-Dist: aiohttp>=3.3
Requires-Dist: aioxmpp>=0.10.4
Requires-Dist: aioconsole>=0.1.15
Requires-Dist: pytz
Provides-Extra: docs
Requires-Dist: sphinxcontrib-trio==1.1.0; extra == "docs"
